embarrassing/__init__.py
embarrassing/main.py
src/__init__.py
src/embarrassing/__init__.py
src/embarrassing/main.py
embarrassing-0.0.11.dist-info/METADATA
embarrassing-0.0.11.dist-info/WHEEL
embarrassing-0.0.11.dist-info/top_level.txt
embarrassing-0.0.11.dist-info/RECORD
