Metadata-Version: 2.1
Name: embarrassing
Version: 0.0.11
Summary: A package to embarrassingly parallelize your code
Home-page: https://github.com/qwertyuu/embarrassing
Author: Raphaël Côté
Author-email: cotlarrc@gmail.com
Classifier: Development Status :: 3 - Alpha
Classifier: Programming Language :: Python :: 3
Classifier: License :: OSI Approved :: MIT License
Classifier: Operating System :: OS Independent
Requires-Python: >=3.6
Requires-Dist: tqdm
Requires-Dist: joblib
